src/__init__.py
src/core/__init__.py
src/core/receiver.py
src/core/sender.py
src/utils/__init__.py
src/utils/config.py
src/utils/encryption.py
src/utils/logger.py
src/utils/network.py
src/utils/progress.py
src/utils/session.py
system_sell-0.1.0.dist-info/METADATA
system_sell-0.1.0.dist-info/WHEEL
system_sell-0.1.0.dist-info/entry_points.txt
system_sell-0.1.0.dist-info/top_level.txt
system_sell-0.1.0.dist-info/RECORD
