Metadata-Version: 2.4
Name: system-sell
Version: 0.1.0
Summary: Secure P2P File Sharing Tool
Home-page: https://github.com/Ayushkiller/System-sell
Author: Ayushkiller
Author-email: your.email@example.com
Classifier: Programming Language :: Python :: 3
Classifier: License :: OSI Approved :: MIT License
Classifier: Operating System :: OS Independent
Requires-Python: >=3.7
Requires-Dist: cryptography
Requires-Dist: qrcode[pil]
Dynamic: author
Dynamic: author-email
Dynamic: classifier
Dynamic: description
Dynamic: description-content-type
Dynamic: home-page
Dynamic: requires-dist
Dynamic: requires-python
Dynamic: summary
